odoo/addons/picking_serial_list/README.rst
odoo/addons/picking_serial_list/__init__.py
odoo/addons/picking_serial_list/__manifest__.py
odoo/addons/picking_serial_list/i18n/es.po
odoo/addons/picking_serial_list/models/__init__.py
odoo/addons/picking_serial_list/models/stock_move.py
odoo/addons/picking_serial_list/models/stock_move_line.py
odoo/addons/picking_serial_list/models/stock_picking.py
odoo/addons/picking_serial_list/models/stock_picking_type.py
odoo/addons/picking_serial_list/static/description/icon.png
odoo/addons/picking_serial_list/views/stock_picking_views.xml
odoo14_addon_picking_serial_list-14.0.3.0.0.dist-info/METADATA
odoo14_addon_picking_serial_list-14.0.3.0.0.dist-info/WHEEL
odoo14_addon_picking_serial_list-14.0.3.0.0.dist-info/top_level.txt
odoo14_addon_picking_serial_list-14.0.3.0.0.dist-info/RECORD
