Metadata-Version: 2.1
Name: odoo14-addon-picking_serial_list
Version: 14.0.3.0.0
Summary: Picking Serial List
Home-page: https://github.com/OCA/pos
Author: Sygel, Odoo Community Association (OCA)
Author-email: support@odoo-community.org
License: AGPL-3
Classifier: Programming Language :: Python
Classifier: Framework :: Odoo
Classifier: Framework :: Odoo :: 14.0
Classifier: License :: OSI Approved :: GNU Affero General Public License v3
Requires-Python: >=3.6
Requires-Dist: odoo<14.1dev,>=14.0a
